{
"type": "FeatureCollection",
"name": "last_week_sightings_2025-W4",
"crs": { "type": "name", "properties": { "name": "urn:ogc:def:crs:OGC:1.3:CRS84" } },
"features": [
{ "type": "Feature", "properties": { "DATETIME": "2025-01-24T02:51:00", "LATITUDE": 48.30298, "LONGITUDE": -123.54802, "WEEK": 4, "YEAR": 2025 }, "geometry": { "type": "Point", "coordinates": [ -123.54802, 48.30298 ] } }
]
}
