{
"type": "FeatureCollection",
"name": "last_week_sightings_2025-W43",
"crs": { "type": "name", "properties": { "name": "urn:ogc:def:crs:OGC:1.3:CRS84" } },
"features": [
{ "type": "Feature", "properties": { "DATETIME": "2025-10-26T01:30:00", "LATITUDE": 48.03573, "LONGITUDE": -122.63019, "WEEK": 43, "YEAR": 2025 }, "geometry": { "type": "Point", "coordinates": [ -122.63019, 48.03573 ] } },
{ "type": "Feature", "properties": { "DATETIME": "2025-10-26T01:47:00", "LATITUDE": 48.02494, "LONGITUDE": -122.62882, "WEEK": 43, "YEAR": 2025 }, "geometry": { "type": "Point", "coordinates": [ -122.62882, 48.02494 ] } }
]
}
